Metadata-Version: 2.1
Name: shazib-seriesbox
Version: 1.0
Summary: Testing installation of Package
Home-page: https://github.com/shazib96/seriesbox_public
Author: Shazib Mustafa
Author-email: shaojoiya@gmail.com
License: MIT
Download-URL: https://github.com/shazib96/seriesbox_public/releases/tag/v1.0
Project-URL: Bug Tracker, https://github.com/shazib96/seriesbox_public/issues
Keywords: pypi,shazib_seriesbox,tutorial
Platform: UNKNOWN
Classifier: Development Status :: 3 - Alpha
Classifier: Intended Audience :: Developers
Classifier: Topic :: Software Development :: Documentation
Classifier: License :: OSI Approved :: MIT License
Classifier: Programming Language :: Python :: 3
Classifier: Programming Language :: Python :: 3.7
Classifier: Programming Language :: Python :: 3.8
Classifier: Programming Language :: Python :: 3.9
